opcodes.vh
// File: variables.vh
// VARIABLES for IMEM AND DMEM

`ifndef OPCODES
`define OPCODES

`define R_TYPE 2'b00
`define I_TYPE 2'b01
`define M_TYPE 2'b01
`define B_TYPE 2'b11

`define ADD 4'b0000
`define SUB 4'b0001

`endif

alu.v

/* verilator lint_off TIMESCALEMOD */
`include "opcodes.vh"

module alu (
    input wire [31:0] input1,
    input wire [31:0] input2,
    input wire [3:0]  alu_sel,
    output reg [31:0] out,
    output reg over,
    output reg under   
);

    reg [31:0] a, b;
    reg [31:0] sum, diff;
    reg [31:0] x, y;
    reg [63:0] mult_result;
    reg [31:0] carry;

    always @(*) begin
        a = input1;
        b = input2;
        out = 32'd0;
        over = 1'b0;
        under = 1'b0;
        sum = 32'd0;
        diff = 32'd0;
        x = 32'd0;
        y = 32'd0;
        carry = 32'd0;
        mult_result = 64'd0;
        case (alu_sel)
            `ADD: begin
                x = a;
                y = b;
                while (y != 0) begin
                    carry = x & y;
                    x = x ^ y;
                    y = carry << 1;
                end
                sum = x;
                out = sum;

                if ((a[31] == 1'b0) && (b[31] == 1'b0) && (out[31] == 1'b1)) begin
                    over  = 1'b1;
                end
                else if ((a[31] == 1'b1) && (b[31] == 1'b1) && (out[31] == 1'b0)) begin
                    under = 1'b1;
                end
            end

            `SUB: begin
                y = ~b;
                carry = 32'd1;
                while (carry != 0) begin
                    x = y;
                    y = carry;
                    carry = x & y;
                    y = x ^ y;
                    carry = carry << 1;
                end
                b = y;

                x = a;
                y = b;
                while (y != 0) begin
                    carry = x & y;
                    x = x ^ y;
                    y = carry << 1;
                end
                diff = x;
                out = diff;

                if ((a[31] == 1'b0) && (input2[31] == 1'b1) && (out[31] == 1'b1)) begin
                    over  = 1'b1;
                end
                else if ((a[31] == 1'b1) && (input2[31] == 1'b0) && (out[31] == 1'b0)) begin
                    under = 1'b1;
                end
            end

            `MUL: begin
                mult_result = $signed(a) * $signed(input2);
                out = mult_result[31:0];

                if (mult_result[63:32] != {32{out[31]}}) begin
                    if (a[31] ^ input2[31]) begin
                        under = 1'b1;
                    end else begin
                        over  = 1'b1;
                    end
                end
            end
            `AND: out = input1 & input2;
            `OR:  out = input1 | input2;
            `XOR: out = input1 ^ input2;
            `NOT: out = ~input1;
            
            `EQ:  out = (input1 == input2) ? 32'd1 : 32'd0;
            `NEQ: out = (input1 != input2) ? 32'd1 : 32'd0;
            `LT:  out = ($signed(input1) <  $signed(input2)) ? 32'd1 : 32'd0;
            `LTE: out = ($signed(input1) <= $signed(input2)) ? 32'd1 : 32'd0;
            `GT:  out = ($signed(input1) >  $signed(input2)) ? 32'd1 : 32'd0;
            `GTE: out = ($signed(input1) >= $signed(input2)) ? 32'd1 : 32'd0;

            default: out = 32'd0;

        endcase
    end

endmodule
/* verilator lint_on TIMESCALEMOD */

tb_alu.v
//This is my ALU test bench to test the ALU.
`timescale 1ns/1ps
`include "opcodes.vh"

module tb_alu;


  reg  [31:0] input1, input2;
  reg  [3:0]  alu_sel;
  wire [31:0] out;
  wire over, under;


  alu dut (
    .input1(input1),
    .input2(input2),
    .alu_sel(alu_sel),
    .out(out),
    .over(over),
    .under(under)
  );

  // This task is to print the results
  task show;
    input [255*8:1] label; 
  begin
    #1; 
    $display("%0s | sel=%0d  A=0x%08x (%0d)  B=0x%08x (%0d)  ->  OUT=0x%08x (%0d)  OVER=%0b UNDER=%0b",
             label, alu_sel,
             input1, $signed(input1),
             input2, $signed(input2),
             out,    $signed(out),
             over, under);
  end
  endtask

  task run_vec;
    input [3:0]  sel;
    input [31:0] a, b;
    input [255*8:1] label;
  begin
    alu_sel = sel;
    input1  = a;
    input2  = b;
    show(label);
  end
  endtask

  initial begin
    //To enable VCD to see waveforms
    $dumpfile("alu_tb.vcd");
    $dumpvars(0, tb_alu);

    $display("=== EE275 ALU RUN ===");

    // UNIT TEST for ADD
    run_vec(`ADD, 32'h0000_0001, 32'h0000_0002, "ADD 1 + 2");
    run_vec(`ADD, 32'h7FFF_FFFF, 32'h0000_0001, "ADD overflow +");
    run_vec(`ADD, 32'h8000_0000, 32'h8000_0000, "ADD overflow -");

    // UNIT TEST FOR SUB
    run_vec(`SUB, 32'h0000_0005, 32'h0000_0003, "SUB 5 - 3");
    run_vec(`SUB, 32'h8000_0000, 32'h7FFF_FFFF, "SUB overflow -");
    run_vec(`SUB, 32'h7FFF_FFFF, 32'h8000_0000, "SUB overflow +");

    // UNIT TEST FOR MUL
    run_vec(`MUL, 32'h0000_0003, 32'h0000_0007, "MUL 3 * 7");
    run_vec(`MUL, 32'h4000_0000, 32'h0000_0004, "MUL overflow +");
    run_vec(`MUL, -32'sd300000000, 32'sd30,     "MUL overflow -");

    // UNIT TEST FOR LOGIC
    run_vec(`AND, 32'hF0F0_F0F0, 32'h0F0F_0F0F, "AND");
    run_vec(`OR,  32'hF0F0_0000, 32'h00F0_0F0F, "OR");
    run_vec(`XOR, 32'hAAAA_AAAA, 32'h5555_5555, "XOR");
    run_vec(`NOT, 32'h0000_00FF, 32'hDEAD_BEEF, "NOT (B ignored)");

    // UNIT TEST FOR COMPARE INSTRUCTIONS
    run_vec(`EQ,   32'd5,  32'd5,  "EQ");
    run_vec(`NEQ,  32'd5,  32'd6,  "NEQ");
    run_vec(`LT,  -32'sd1, 32'sd1, "LT  -1 < 1");
    run_vec(`LTE, -32'sd1, -32'sd1,"LTE -1 <= -1");
    run_vec(`GT,   32'sd7, -32'sd2,"GT   7 > -2");
    run_vec(`GTE,  32'sd7,  32'sd7,"GTE  7 >= 7");

    $display("=== Done ===");
    $finish;
  end

endmodule

alu_tb.vcd
$version Generated by VerilatedVcd $end
$timescale 1ps $end
 $scope module TOP $end
  $scope module tb_alu $end
   $var wire 32 / input1 [31:0] $end
   $var wire 32 0 input2 [31:0] $end
   $var wire 4 1 alu_sel [3:0] $end
   $var wire 32 # out [31:0] $end
   $var wire 1 $ over $end
   $var wire 1 % under $end
   $scope module dut $end
    $var wire 32 / input1 [31:0] $end
    $var wire 32 0 input2 [31:0] $end
    $var wire 4 1 alu_sel [3:0] $end
    $var wire 32 # out [31:0] $end
    $var wire 1 $ over $end
    $var wire 1 % under $end
    $var wire 32 & a [31:0] $end
    $var wire 32 ' b [31:0] $end
    $var wire 32 ( sum [31:0] $end
    $var wire 32 ) diff [31:0] $end
    $var wire 32 * x [31:0] $end
    $var wire 32 + y [31:0] $end
    $var wire 64 , mult_result [63:0] $end
    $var wire 32 . carry [31:0] $end
   $upscope $end
  $upscope $end
 $upscope $end
$enddefinitions $end


#0
b00000000000000000000000000000011 #
0$
0%
b00000000000000000000000000000001 &
b00000000000000000000000000000010 '
b00000000000000000000000000000011 (
b00000000000000000000000000000000 )
b00000000000000000000000000000011 *
b00000000000000000000000000000000 +
b0000000000000000000000000000000000000000000000000000000000000000 ,
b00000000000000000000000000000000 .
b00000000000000000000000000000001 /
b00000000000000000000000000000010 0
b0000 1
#1000
b10000000000000000000000000000000 #
1$
b01111111111111111111111111111111 &
b00000000000000000000000000000001 '
b10000000000000000000000000000000 (
b10000000000000000000000000000000 *
b01111111111111111111111111111111 /
b00000000000000000000000000000001 0
#2000
b00000000000000000000000000000000 #
0$
1%
b10000000000000000000000000000000 &
b10000000000000000000000000000000 '
b00000000000000000000000000000000 (
b00000000000000000000000000000000 *
b10000000000000000000000000000000 .
b10000000000000000000000000000000 /
b10000000000000000000000000000000 0
#3000
b00000000000000000000000000000010 #
0%
b00000000000000000000000000000101 &
b11111111111111111111111111111101 '
b00000000000000000000000000000010 )
b00000000000000000000000000000010 *
b00000000000000000000000000000101 /
b00000000000000000000000000000011 0
b0001 1
#4000
b00000000000000000000000000000001 #
1%
b10000000000000000000000000000000 &
b10000000000000000000000000000001 '
b00000000000000000000000000000001 )
b00000000000000000000000000000001 *
b10000000000000000000000000000000 /
b01111111111111111111111111111111 0
#5000
b11111111111111111111111111111111 #
1$
0%
b01111111111111111111111111111111 &
b10000000000000000000000000000000 '
b11111111111111111111111111111111 )
b11111111111111111111111111111111 *
b00000000000000000000000000000000 .
b01111111111111111111111111111111 /
b10000000000000000000000000000000 0
#6000
b00000000000000000000000000010101 #
0$
b00000000000000000000000000000011 &
b00000000000000000000000000000111 '
b00000000000000000000000000000000 )
b00000000000000000000000000000000 *
b0000000000000000000000000000000000000000000000000000000000010101 ,
b00000000000000000000000000000011 /
b00000000000000000000000000000111 0
b0010 1
#7000
b00000000000000000000000000000000 #
1$
b01000000000000000000000000000000 &
b00000000000000000000000000000100 '
b0000000000000000000000000000000100000000000000000000000000000000 ,
b01000000000000000000000000000000 /
b00000000000000000000000000000100 0
#8000
b11100111100011101110011000000000 #
0$
1%
b11101110000111100101110100000000 &
b00000000000000000000000000011110 '
b1111111111111111111111111111110111100111100011101110011000000000 ,
b11101110000111100101110100000000 /
b00000000000000000000000000011110 0
#9000
b00000000000000000000000000000000 #
0%
b11110000111100001111000011110000 &
b00001111000011110000111100001111 '
b0000000000000000000000000000000000000000000000000000000000000000 ,
b11110000111100001111000011110000 /
b00001111000011110000111100001111 0
b0011 1
#10000
b11110000111100000000111100001111 #
b11110000111100000000000000000000 &
b00000000111100000000111100001111 '
b11110000111100000000000000000000 /
b00000000111100000000111100001111 0
b0100 1
#11000
b11111111111111111111111111111111 #
b10101010101010101010101010101010 &
b01010101010101010101010101010101 '
b10101010101010101010101010101010 /
b01010101010101010101010101010101 0
b0101 1
#12000
b11111111111111111111111100000000 #
b00000000000000000000000011111111 &
b11011110101011011011111011101111 '
b00000000000000000000000011111111 /
b11011110101011011011111011101111 0
b0110 1
#13000
b00000000000000000000000000000001 #
b00000000000000000000000000000101 &
b00000000000000000000000000000101 '
b00000000000000000000000000000101 /
b00000000000000000000000000000101 0
b0111 1
#14000
b00000000000000000000000000000110 '
b00000000000000000000000000000110 0
b1000 1
#15000
b11111111111111111111111111111111 &
b00000000000000000000000000000001 '
b11111111111111111111111111111111 /
b00000000000000000000000000000001 0
b1001 1
#16000
b11111111111111111111111111111111 '
b11111111111111111111111111111111 0
b1010 1
#17000
b00000000000000000000000000000111 &
b11111111111111111111111111111110 '
b00000000000000000000000000000111 /
b11111111111111111111111111111110 0
b1011 1
#18000
b00000000000000000000000000000111 '
b00000000000000000000000000000111 0
b1100 1
